README.md
setup.py
onegram/__init__.py
onegram/actions.py
onegram/constants.py
onegram/exceptions.py
onegram/queries.py
onegram/session.py
onegram/settings.py
onegram.egg-info/PKG-INFO
onegram.egg-info/SOURCES.txt
onegram.egg-info/dependency_links.txt
onegram.egg-info/requires.txt
onegram.egg-info/top_level.txt
onegram/utils/__init__.py
onegram/utils/ratelimit.py
onegram/utils/validation.py