Metadata-Version: 1.2
Name: onegram
Version: 1.2.0
Summary: A simplistic api-like instagram bot powered by requests
Home-page: https://github.com/pauloromeira/onegram
Author: Paulo Romeira
Author-email: paulo@pauloromeira.com
License: UNKNOWN
Platform: UNKNOWN
Classifier: Development Status :: 3 - Alpha
Classifier: Intended Audience :: Developers
Classifier: Topic :: Software Development :: Build Tools
Classifier: License :: OSI Approved :: MIT License
Classifier: Programming Language :: Python :: 3.6
Requires-Python: >=3.6
